{"msg": "\u767b\u5f55\u6210\u529f", "nr_name": "nr_227k82lq7", "code": "1", "unionid": "o4empt8bofBbXrIWdRbnBhrKr7k8", "validate_code": "E8FFBBA3747786FDE30B8EC08B1E50C0", "box_limit": "100", "roles": "", "admin": "0", "insert_time": "2020-03-13 14:01:00", "source": "\u4e3b\u7ad9\u9996\u9875\u624b\u673a\u53f7\u6ce8\u518c", "pass_flag": "0", "uuid": "FCBA2883847EB0A4509B8FF6809422C3", "update_time": "2020-03-13 14:01:00", "user_type": "0", "headimgurl": "http://thirdwx.qlogo.cn/mmopen/k6KhCohpOAeofzGicJvtHa0fvIxZ5KfkYibY9rJhQjMNWCkYxthp5UH5ic9haakbiaFiazAGDrnT5O8TzKAK3NAQUdlUsp9zrnGow/132", "id": "1547727", "wxopenid": "oFCwWw3RbJexH3g9oOVdGatcAeWw", "rank_box_limit": "100", "sex": "0", "rank_level": "0", "token": "D1A829A6B9079B6F9101FE85C4E8F265", "card_status": "0", "phone_login": "17310198083", "card_check_fail_count": "0", "nr_id": "nr_227k82lq7", "phone": "17310198083", "rank_limit": "3", "nick_name": "Leo Li", "img_status": "1", "name": "nr_227k82lq7@xx.com", "invite_code": "03D5k8", "status": "1"}